nafnetlib/__init__.py
nafnetlib/conf.py
nafnetlib/core.py
nafnetlib/logger.py
nafnetlib/utils.py
nafnetlib/basic_sr/__init__.py
nafnetlib/basic_sr/base_model.py
nafnetlib/models/__init__.py
nafnetlib/models/misc.py
nafnetlib/models/nafnet.py
nafnetlib/models/restoration.py
nafnetlib/models/utils.py
nafnetlib-0.1.0.dist-info/LICENSE
nafnetlib-0.1.0.dist-info/METADATA
nafnetlib-0.1.0.dist-info/WHEEL
nafnetlib-0.1.0.dist-info/top_level.txt
nafnetlib-0.1.0.dist-info/RECORD
